LICENSE
README.md
benchmark.py
events_helper.py
setup.py
hecho_events/main.py
hecho_events/requirements.txt
hecho_events.egg-info/PKG-INFO
hecho_events.egg-info/SOURCES.txt
hecho_events.egg-info/dependency_links.txt
hecho_events.egg-info/requires.txt
hecho_events.egg-info/top_level.txt