Metadata-Version: 2.1
Name: hecho-events
Version: 1.3.1
Summary: Event Broker Rasa
Home-page: UNKNOWN
Author: Compasso UOL
Author-email: hecho.teste@outlook.com
License: MIT License
Keywords: Pacote hecho
Platform: UNKNOWN
License-File: LICENSE
